bmp280lp/__init__.py
bmp280lp/bmp280lp.py
bmp280lp-0.1.6.dist-info/LICENSE
bmp280lp-0.1.6.dist-info/METADATA
bmp280lp-0.1.6.dist-info/WHEEL
bmp280lp-0.1.6.dist-info/top_level.txt
bmp280lp-0.1.6.dist-info/RECORD
