Metadata-Version: 2.1
Name: bmp280lp
Version: 0.1.6
Summary: A library to use BMP280 and BME280 sensor with bus and address settings
Author-email: Laurent Pastor <l.pastor@free.fr>
License: MIT
Classifier: Programming Language :: Python :: 3
Classifier: License :: OSI Approved :: MIT License
Classifier: Operating System :: OS Independent
Requires-Python: >=3.6
License-File: LICENSE
Requires-Dist: smbus2
